{
"configuration" : {
  "stop_bit": 1,
  "method": "rtu",
  "port": "/dev/ttyUSB0",
  "bytesize": 8,
  "parity": "N",
  "baudrate": 9600,
  "serviceURL":"http://ctoceu.cyient.com:3290//sitesurvey_rest/update_data",
  "Data_interval":"60"


},
  "Battery":
  {
  "Gatewayname":"Madhapur",
  "DeviceType":"Analog",
  "RegisterType":"holding",
  "Register_address": "0X17",
  "Slave_id": "1",
  "Multiplier":"0.001",
  "Threshold":"23.5"
  },
  "PIR":
{
  "Gatewayname":"Madhapur",
  "DeviceType":"Digital",
  "PIN":4,
  "Mode":"Pull_down"
}

}